exceljet_client/__init__.py
exceljet_client/client.py
exceljet_client/exceptions.py
exceljet_client/models.py
exceljet_client/utils.py
exceljet_client-0.1.6.dist-info/METADATA
exceljet_client-0.1.6.dist-info/WHEEL
exceljet_client-0.1.6.dist-info/top_level.txt
exceljet_client-0.1.6.dist-info/RECORD
