Metadata-Version: 2.4
Name: exceljet-client
Version: 0.1.6
Summary: Client library for the ExcelJet API
Author-email: Exceljet Team <kurt@exceljet.net>
License: MIT
Project-URL: Homepage, https://github.com/exceljet2/exceljet-client
Project-URL: Documentation, https://docs.exceljet.com/api
Classifier: Programming Language :: Python :: 3
Classifier: License :: OSI Approved :: MIT License
Classifier: Operating System :: OS Independent
Requires-Python: >=3.8
Requires-Dist: requests>=2.32.3
Requires-Dist: pydantic>=2.11.3
Provides-Extra: dev
Requires-Dist: pytest>=8.3.5; extra == "dev"
Requires-Dist: build>=1.2.2; extra == "dev"
Requires-Dist: responses>=0.25.7; extra == "dev"
Requires-Dist: twine>=6.1.0; extra == "dev"
Requires-Dist: bump2version>=1.0.1; extra == "dev"
